{"v":"5.6.6","fr":25,"ip":0,"op":24,"w":414,"h":896,"nm":"Idle Preview","ddd":0,"assets":[],"layers":[{"ddd":0,"ind":1,"ty":4,"nm":"Demon Vector contornos 2","sr":1,"ks":{"o":{"a":0,"k":100,"ix":11},"r":{"a":0,"k":0,"ix":10},"p":{"a":1,"k":[{"i":{"x":0.667,"y":1},"o":{"x":0.333,"y":0},"t":0,"s":[208,592,0],"to":[0,0,0],"ti":[0,-4.586,0]},{"i":{"x":0.667,"y":1},"o":{"x":0.333,"y":0},"t":10,"s":[208,612.757,0],"to":[0,4.581,0],"ti":[0,0,0]},{"t":24,"s":[208,592,0]}],"ix":2},"a":{"a":0,"k":[208,603,0],"ix":1},"s":{"a":0,"k":[100,100,100],"ix":6}},"ao":0,"shapes":[{"ty":"gr","it":[{"ind":0,"ty":"sh","ix":1,"ks":{"a":0,"k":{"i":[[0,0],[0,0]],"o":[[0,0],[0,0]],"v":[[-4.903,-4.297],[4.904,4.298]],"c":false},"ix":2},"nm":"Caminho 1","mn":"ADBE Vector Shape - Group","hd":false},{"ty":"st","c":{"a":0,"k":[0.957000014361,0.638999968884,0.736999990426,1],"ix":3},"o":{"a":0,"k":100,"ix":4},"w":{"a":0,"k":4,"ix":5},"lc":2,"lj":1,"ml":10,"bm":0,"nm":"Traçado 1","mn":"ADBE Vector Graphic - Stroke","hd":false},{"ty":"tr","p":{"a":0,"k":[243.268,445.047],"ix":2},"a":{"a":0,"k":[0,0],"ix":1},"s":{"a":0,"k":[100,100],"ix":3},"r":{"a":0,"k":0,"ix":6},"o":{"a":0,"k":100,"ix":7},"sk":{"a":0,"k":0,"ix":4},"sa":{"a":0,"k":0,"ix":5},"nm":"Transformar"}],"nm":"Grupo 1","np":2,"cix":2,"bm":0,"ix":2,"mn":"ADBE Vector Group","hd":false},{"ty":"gr","it":[{"ind":0,"ty":"sh","ix":1,"ks":{"a":0,"k":{"i":[[0,0],[0,0]],"o":[[0,0],[0,0]],"v":[[-6.244,-5.486],[6.244,5.486]],"c":false},"ix":2},"nm":"Caminho 1","mn":"ADBE Vector Shape - Group","hd":false},{"ty":"st","c":{"a":0,"k":[0.957000014361,0.638999968884,0.736999990426,1],"ix":3},"o":{"a":0,"k":100,"ix":4},"w":{"a":0,"k":4,"ix":5},"lc":2,"lj":1,"ml":10,"bm":0,"nm":"Traçado 1","mn":"ADBE Vector Graphic - Stroke","hd":false},{"ty":"tr","p":{"a":0,"k":[250.029,441.669],"ix":2},"a":{"a":0,"k":[0,0],"ix":1},"s":{"a":0,"k":[100,100],"ix":3},"r":{"a":0,"k":0,"ix":6},"o":{"a":0,"k":100,"ix":7},"sk":{"a":0,"k":0,"ix":4},"sa":{"a":0,"k":0,"ix":5},"nm":"Transformar"}],"nm":"Grupo 2","np":2,"cix":2,"bm":0,"ix":3,"mn":"ADBE Vector Group","hd":false},{"ty":"gr","it":[{"ind":0,"ty":"sh","ix":1,"ks":{"a":0,"k":{"i":[[0,0],[0,0]],"o":[[0,0],[0,0]],"v":[[-4.863,-4.12],[4.863,4.12]],"c":false},"ix":2},"nm":"Caminho 1","mn":"ADBE Vector Shape - Group","hd":false},{"ty":"st","c":{"a":0,"k":[0.957000014361,0.638999968884,0.736999990426,1],"ix":3},"o":{"a":0,"k":100,"ix":4},"w":{"a":0,"k":4,"ix":5},"lc":2,"lj":1,"ml":10,"bm":0,"nm":"Traçado 1","mn":"ADBE Vector Graphic - Stroke","hd":false},{"ty":"tr","p":{"a":0,"k":[256.07,438.267],"ix":2},"a":{"a":0,"k":[0,0],"ix":1},"s":{"a":0,"k":[100,100],"ix":3},"r":{"a":0,"k":0,"ix":6},"o":{"a":0,"k":100,"ix":7},"sk":{"a":0,"k":0,"ix":4},"sa":{"a":0,"k":0,"ix":5},"nm":"Transformar"}],"nm":"Grupo 3","np":2,"cix":2,"bm":0,"ix":4,"mn":"ADBE Vector Group","hd":false},{"ty":"gr","it":[{"ind":0,"ty":"sh","ix":1,"ks":{"a":0,"k":{"i":[[0,0],[0,0]],"o":[[0,0],[0,0]],"v":[[4.903,-4.298],[-4.903,4.297]],"c":false},"ix":2},"nm":"Caminho 1","mn":"ADBE Vector Shape - Group","hd":false},{"ty":"st","c":{"a":0,"k":[0.957000014361,0.638999968884,0.736999990426,1],"ix":3},"o":{"a":0,"k":100,"ix":4},"w":{"a":0,"k":4,"ix":5},"lc":2,"lj":1,"ml":10,"bm":0,"nm":"Traçado 1","mn":"ADBE Vector Graphic - Stroke","hd":false},{"ty":"tr","p":{"a":0,"k":[147.427,439.159],"ix":2},"a":{"a":0,"k":[0,0],"ix":1},"s":{"a":0,"k":[100,100],"ix":3},"r":{"a":0,"k":0,"ix":6},"o":{"a":0,"k":100,"ix":7},"sk":{"a":0,"k":0,"ix":4},"sa":{"a":0,"k":0,"ix":5},"nm":"Transformar"}],"nm":"Grupo 4","np":2,"cix":2,"bm":0,"ix":5,"mn":"ADBE Vector Group","hd":false},{"ty":"gr","it":[{"ind":0,"ty":"sh","ix":1,"ks":{"a":0,"k":{"i":[[0,0],[0,0]],"o":[[0,0],[0,0]],"v":[[6.244,-5.486],[-6.244,5.486]],"c":false},"ix":2},"nm":"Caminho 1","mn":"ADBE Vector Shape - Group","hd":false},{"ty":"st","c":{"a":0,"k":[0.957000014361,0.638999968884,0.736999990426,1],"ix":3},"o":{"a":0,"k":100,"ix":4},"w":{"a":0,"k":4,"ix":5},"lc":2,"lj":1,"ml":10,"bm":0,"nm":"Traçado 1","mn":"ADBE Vector Graphic - Stroke","hd":false},{"ty":"tr","p":{"a":0,"k":[140.665,435.781],"ix":2},"a":{"a":0,"k":[0,0],"ix":1},"s":{"a":0,"k":[100,100],"ix":3},"r":{"a":0,"k":0,"ix":6},"o":{"a":0,"k":100,"ix":7},"sk":{"a":0,"k":0,"ix":4},"sa":{"a":0,"k":0,"ix":5},"nm":"Transformar"}],"nm":"Grupo 5","np":2,"cix":2,"bm":0,"ix":6,"mn":"ADBE Vector Group","hd":false},{"ty":"gr","it":[{"ind":0,"ty":"sh","ix":1,"ks":{"a":0,"k":{"i":[[0,0],[0,0]],"o":[[0,0],[0,0]],"v":[[4.863,-4.12],[-4.864,4.12]],"c":false},"ix":2},"nm":"Caminho 1","mn":"ADBE Vector Shape - Group","hd":false},{"ty":"st","c":{"a":0,"k":[0.957000014361,0.638999968884,0.736999990426,1],"ix":3},"o":{"a":0,"k":100,"ix":4},"w":{"a":0,"k":4,"ix":5},"lc":2,"lj":1,"ml":10,"bm":0,"nm":"Traçado 1","mn":"ADBE Vector Graphic - Stroke","hd":false},{"ty":"tr","p":{"a":0,"k":[134.624,432.378],"ix":2},"a":{"a":0,"k":[0,0],"ix":1},"s":{"a":0,"k":[100,100],"ix":3},"r":{"a":0,"k":0,"ix":6},"o":{"a":0,"k":100,"ix":7},"sk":{"a":0,"k":0,"ix":4},"sa":{"a":0,"k":0,"ix":5},"nm":"Transformar"}],"nm":"Grupo 6","np":2,"cix":2,"bm":0,"ix":7,"mn":"ADBE Vector Group","hd":false},{"ty":"gr","it":[{"ind":0,"ty":"sh","ix":1,"ks":{"a":0,"k":{"i":[[0,2.71],[-2.71,0],[0,-2.71],[2.71,0]],"o":[[0,-2.71],[2.71,0],[0,2.71],[-2.71,0]],"v":[[-4.906,0],[0.001,-4.907],[4.906,0],[0.001,4.907]],"c":true},"ix":2},"nm":"Caminho 1","mn":"ADBE Vector Shape - Group","hd":false},{"ty":"fl","c":{"a":0,"k":[1,1,1,1],"ix":4},"o":{"a":0,"k":100,"ix":5},"r":1,"bm":0,"nm":"Preenchimento 1","mn":"ADBE Vector Graphic - Fill","hd":false},{"ty":"tr","p":{"a":0,"k":[171.974,384.12],"ix":2},"a":{"a":0,"k":[0,0],"ix":1},"s":{"a":0,"k":[100,100],"ix":3},"r":{"a":0,"k":0,"ix":6},"o":{"a":0,"k":100,"ix":7},"sk":{"a":0,"k":0,"ix":4},"sa":{"a":0,"k":0,"ix":5},"nm":"Transformar"}],"nm":"Grupo 7","np":2,"cix":2,"bm":0,"ix":8,"mn":"ADBE Vector Group","hd":false},{"ty":"gr","it":[{"ind":0,"ty":"sh","ix":1,"ks":{"a":0,"k":{"i":[[0,10.659],[-10.659,0],[0,-10.659],[10.659,0]],"o":[[0,-10.659],[10.659,0],[0,10.659],[-10.659,0]],"v":[[-19.3,0],[0,-19.3],[19.3,0],[0,19.3]],"c":true},"ix":2},"nm":"Caminho 1","mn":"ADBE Vector Shape - Group","hd":false},{"ty":"fl","c":{"a":0,"k":[0,0,0,1],"ix":4},"o":{"a":0,"k":100,"ix":5},"r":1,"bm":0,"nm":"Preenchimento 1","mn":"ADBE Vector Graphic - Fill","hd":false},{"ty":"tr","p":{"a":0,"k":[183.096,396.551],"ix":2},"a":{"a":0,"k":[0,0],"ix":1},"s":{"a":0,"k":[100,100],"ix":3},"r":{"a":0,"k":0,"ix":6},"o":{"a":0,"k":100,"ix":7},"sk":{"a":0,"k":0,"ix":4},"sa":{"a":0,"k":0,"ix":5},"nm":"Transformar"}],"nm":"Grupo 8","np":2,"cix":2,"bm":0,"ix":9,"mn":"ADBE Vector Group","hd":false},{"ty":"gr","it":[{"ind":0,"ty":"sh","ix":1,"ks":{"a":0,"k":{"i":[[0,18.428],[-18.428,0],[0,-18.427],[18.428,0]],"o":[[0,-18.427],[18.428,0],[0,18.428],[-18.428,0]],"v":[[-33.366,0],[0,-33.366],[33.366,0],[0,33.366]],"c":true},"ix":2},"nm":"Caminho 1","mn":"ADBE Vector Shape - Group","hd":false},{"ty":"fl","c":{"a":0,"k":[1,1,1,1],"ix":4},"o":{"a":0,"k":100,"ix":5},"r":1,"bm":0,"nm":"Preenchimento 1","mn":"ADBE Vector Graphic - Fill","hd":false},{"ty":"tr","p":{"a":0,"k":[191.274,394.261],"ix":2},"a":{"a":0,"k":[0,0],"ix":1},"s":{"a":0,"k":[100,100],"ix":3},"r":{"a":0,"k":0,"ix":6},"o":{"a":0,"k":100,"ix":7},"sk":{"a":0,"k":0,"ix":4},"sa":{"a":0,"k":0,"ix":5},"nm":"Transformar"}],"nm":"Grupo 9","np":2,"cix":2,"bm":0,"ix":10,"mn":"ADBE Vector Group","hd":false}],"ip":0,"op":549,"st":0,"bm":0},{"ddd":0,"ind":2,"ty":4,"nm":"Demon Vector contornos","sr":1,"ks":{"o":{"a":0,"k":100,"ix":11},"r":{"a":0,"k":0,"ix":10},"p":{"a":1,"k":[{"i":{"x":0.667,"y":1},"o":{"x":0.333,"y":0},"t":0,"s":[208,592,0],"to":[0,0,0],"ti":[0,-4.586,0]},{"i":{"x":0.667,"y":1},"o":{"x":0.333,"y":0},"t":10.051,"s":[208,612.757,0],"to":[0,4.581,0],"ti":[0,0,0]},{"t":24,"s":[208,592,0]}],"ix":2},"a":{"a":0,"k":[208,603,0],"ix":1},"s":{"a":0,"k":[102.155,98.707,100],"ix":6}},"ao":0,"shapes":[{"ty":"gr","it":[{"ind":0,"ty":"sh","ix":1,"ks":{"a":0,"k":{"i":[[9.066,0.071],[21.695,-16.334],[1.758,10.95],[0.922,-3.225],[-4.013,-11.308],[5.152,-17.388],[1.044,-6.811],[1.43,-10.975],[0.083,-5.104],[-0.065,-1.932],[-57.451,0],[0,57.451],[0.001,0.041],[0,0],[0,0],[1.592,7.912],[4.137,11.975],[2.872,5.534],[10.415,36.449],[0.531,-3.312],[8.709,-9.711],[5.514,3.178]],"o":[[-8.231,-0.064],[-6.118,-10.4],[-0.531,-3.312],[-8.301,29.054],[-3.72,9.209],[-6.982,23.564],[-2.321,15.141],[-0.168,1.289],[-0.024,1.52],[0,57.451],[57.451,0],[0,-1.498],[0,0],[-0.005,-19.386],[-0.921,-4.184],[-8.231,-40.866],[-0.872,-2.523],[4.234,-8.277],[-0.921,-3.225],[-2.108,13.141],[-4.167,-3.856],[-18.618,-10.732]],"v":[[0.053,-128.984],[-57.799,-112.829],[-69.059,-149.423],[-75.166,-149.768],[-75.689,-88.925],[-88.268,-49.821],[-99.39,-0.753],[-103.315,33.921],[-104.053,44.132],[-103.969,48.969],[0.053,152.993],[104.077,48.969],[104.04,45.817],[104.04,45.816],[98.843,5.135],[94.933,-13.423],[84.45,-69.448],[78.992,-82.082],[81.386,-149.768],[75.279,-149.423],[60.012,-107.247],[45.54,-117.936]],"c":true},"ix":2},"nm":"Caminho 1","mn":"ADBE Vector Shape - Group","hd":false},{"ty":"fl","c":{"a":0,"k":[0,0,0,1],"ix":4},"o":{"a":0,"k":100,"ix":5},"r":1,"bm":0,"nm":"Preenchimento 1","mn":"ADBE Vector Graphic - Fill","hd":false},{"ty":"tr","p":{"a":0,"k":[206.922,448.007],"ix":2},"a":{"a":0,"k":[0,0],"ix":1},"s":{"a":0,"k":[100,100],"ix":3},"r":{"a":0,"k":0,"ix":6},"o":{"a":0,"k":100,"ix":7},"sk":{"a":0,"k":0,"ix":4},"sa":{"a":0,"k":0,"ix":5},"nm":"Transformar"}],"nm":"Grupo 10","np":2,"cix":2,"bm":0,"ix":1,"mn":"ADBE Vector Group","hd":false}],"ip":0,"op":549,"st":0,"bm":0}],"markers":[]}